README.md
setup.py
cingta_django_sso.egg-info/PKG-INFO
cingta_django_sso.egg-info/SOURCES.txt
cingta_django_sso.egg-info/dependency_links.txt
cingta_django_sso.egg-info/requires.txt
cingta_django_sso.egg-info/top_level.txt
sso_server/__init__.py
sso_server/admin.py
sso_server/apps.py
sso_server/generate_key.py
sso_server/models.py
sso_server/tests.py
sso_server/utils.py
sso_server/views.py
sso_server/migrations/__init__.py